setup.py
samplify/__init__.py
samplify/energy.py
samplify/imperial.py
samplify/si.py
samplify/timeseries.py
samplify/util.py
samplify.egg-info/PKG-INFO
samplify.egg-info/SOURCES.txt
samplify.egg-info/dependency_links.txt
samplify.egg-info/top_level.txt
samplify/libs/__init__.py
samplify/test/__init__.py
samplify/test/__main__.py
samplify/test/imperial.py
samplify/test/si.py