Metadata-Version: 1.1
Name: samplify
Version: 0.1.0
Summary: Take, save, and manipulate objects that store both maginitude and measurement information.
Home-page: http://github.com/BennettRand/Samplify/
Author: Bennett Rand
Author-email: bennett.h.rand@gmail.com
License: MIT
Platform: Linux
Platform: Win
Classifier: License :: OSI Approved :: MIT License
Classifier: Topic :: Utilities
Classifier: Operating System :: OS Independent
